hflm/__init__.py
hflm/huggingface_model.py
hflm/model.py
hflm/utils.py
hflm/lm_gen/__main__.py
hflm/lm_prob/__main__.py
hflm-0.0.9.dist-info/LICENSE
hflm-0.0.9.dist-info/METADATA
hflm-0.0.9.dist-info/WHEEL
hflm-0.0.9.dist-info/entry_points.txt
hflm-0.0.9.dist-info/top_level.txt
hflm-0.0.9.dist-info/RECORD
