Metadata-Version: 2.1
Name: hflm
Version: 0.0.9
Summary: A simple library for working with Hugging Face models.
Author: Richard Kelley, Duncan Wilson
License: BSD License
Project-URL: Homepage, https://github.com/RichardKelley/hflm
Classifier: License :: OSI Approved :: BSD License
Classifier: Intended Audience :: Science/Research
Classifier: Topic :: Scientific/Engineering :: Artificial Intelligence
Requires-Python: >=3.7
License-File: LICENSE
Requires-Dist: torch>=2.0.0
Requires-Dist: transformers>=4.36.2
Requires-Dist: accelerate>=0.26.1
Requires-Dist: bitsandbytes>=0.42.0
Requires-Dist: sentencepiece>=0.1.99
Requires-Dist: protobuf>=4.25.2
Requires-Dist: tqdm>=4.0.0
Provides-Extra: dev
Requires-Dist: pytest>=8.0.0; extra == "dev"
